e2eqavn/__init__.py
e2eqavn/cli.py
e2eqavn/keywords.py
e2eqavn/datasets/MRCDataset.py
e2eqavn/datasets/TripletDataset.py
e2eqavn/datasets/__init__.py
e2eqavn/datasets/data_collator.py
e2eqavn/documents/__init__.py
e2eqavn/documents/corpus.py
e2eqavn/documents/document_store.py
e2eqavn/evaluate/__init__.py
e2eqavn/evaluate/bm25_evaluate_retrieval.py
e2eqavn/evaluate/information_retrieval_evaluator_custom.py
e2eqavn/evaluate/mrc_evaluator.py
e2eqavn/mrc/__init__.py
e2eqavn/mrc/base.py
e2eqavn/mrc/mrc_model.py
e2eqavn/pipeline/__init__.py
e2eqavn/pipeline/e2e_question_answering.py
e2eqavn/pipeline/pipeline.py
e2eqavn/processor/__init__.py
e2eqavn/processor/bm25.py
e2eqavn/processor/chunk.py
e2eqavn/processor/qa_ext_processor.py
e2eqavn/processor/retrieval_sampling.py
e2eqavn/retrieval/__init__.py
e2eqavn/retrieval/base.py
e2eqavn/retrieval/bm25_retrieval.py
e2eqavn/retrieval/sbert_retrieval.py
e2eqavn/utils/__init__.py
e2eqavn/utils/calculate.py
e2eqavn/utils/io.py
e2eqavn/utils/preprocess.py
test/__init__.py
test/test_chunking.py
e2eqavn-3.4.dist-info/METADATA
e2eqavn-3.4.dist-info/WHEEL
e2eqavn-3.4.dist-info/entry_points.txt
e2eqavn-3.4.dist-info/top_level.txt
e2eqavn-3.4.dist-info/RECORD
