Metadata-Version: 2.1
Name: e2eqavn
Version: 3.4
Summary: e2eqavn is end to end pipeline for question answering
Author: khanhdm
Author-email: khanhc1k36@gmail.com
Requires-Python: >3.6.0
Requires-Dist: numpy
Requires-Dist: PyYAML
Requires-Dist: sentence-transformers
Requires-Dist: torch
Requires-Dist: tqdm
Requires-Dist: networkx
Requires-Dist: pandas
Requires-Dist: datasets
Requires-Dist: nltk
Requires-Dist: python-dotenv
Requires-Dist: wandb
Requires-Dist: kaggle
Requires-Dist: matplotlib
Requires-Dist: seaborn
Requires-Dist: accelerate
Requires-Dist: protobuf (==3.20)
Requires-Dist: colorlog
Requires-Dist: fastapi
Requires-Dist: uvicorn
Requires-Dist: pymongo[srv]
